unpdfer
