Metadata-Version: 1.1
Name: unpdfer
Version: 0.0.4
Summary: Converts pdfs to text
Home-page: https://github.com/thequbit/unpdfer
Author: Timothy Duffy
Author-email: tim@timduffy.me
License: GPL3
Platform: any
Classifier: Development Status :: 4 - Beta
Classifier: Environment :: Console
Classifier: Intended Audience :: Developers
Classifier: License :: OSI Approved :: GNU General Public License v3 (GPLv3)
Classifier: Operating System :: POSIX
